{
  "project_info": {
    "project_number": "1017763539160",
    "firebase_url": "https://third-current-445.firebaseio.com",
    "project_id": "third-current-445",
    "storage_bucket": "third-current-445.appspot.com"
  },
  "client": [
    {
      "client_info": {
        "mobilesdk_app_id": "1:1017763539160:android:1365cb0091c2f5d7",
        "android_client_info": {
          "package_name": "com.streethawk.streethawkapp"
        }
      },
      "oauth_client": [
        {
          "client_id": "1017763539160-rualcf3s42cf3daeg1l9i6v4vu854peh.apps.googleusercontent.com",
          "client_type": 3
        }
      ],
      "api_key": [
        {
          "current_key": "AIzaSyAf7jUg4L7CLTT6tdWcrZYd1m4XCjUENlo"
        }
      ],
      "services": {
        "analytics_service": {
          "status": 1
        },
        "appinvite_service": {
          "status": 1,
          "other_platform_oauth_client": []
        },
        "ads_service": {
          "status": 2
        }
      }
    }
  ],
  "configuration_version": "1"
}